AUTHORS
LICENSE
MANIFEST.in
README.rst
setup.cfg
setup.py
versioneer.py
indico/__init__.py
indico/_version.py
indico/errors.py
indico/client/__init__.py
indico/client/client.py
indico/client/request.py
indico/config/__init__.py
indico/config/config.py
indico/filters/__init__.py
indico/http/__init__.py
indico/http/client.py
indico/http/retry.py
indico/http/serialization.py
indico/queries/__init__.py
indico/queries/custom_blueprint.py
indico/queries/datasets.py
indico/queries/document_report.py
indico/queries/documents.py
indico/queries/example.py
indico/queries/export.py
indico/queries/forms.py
indico/queries/integration.py
indico/queries/jobs.py
indico/queries/model_export.py
indico/queries/model_import.py
indico/queries/questionnaire.py
indico/queries/storage.py
indico/queries/submission.py
indico/queries/usermetrics.py
indico/queries/workflow.py
indico/queries/workflow_components.py
indico/queries/workflow_metrics.py
indico/queries/model_groups/__init__.py
indico/queries/model_groups/metrics.py
indico/queries/model_groups/model_groups.py
indico/types/__init__.py
indico/types/base.py
indico/types/custom_blueprint.py
indico/types/datafile.py
indico/types/dataset.py
indico/types/document_report.py
indico/types/export.py
indico/types/integration.py
indico/types/jobs.py
indico/types/model.py
indico/types/model_export.py
indico/types/model_group.py
indico/types/model_metrics.py
indico/types/output_file.py
indico/types/questionnaire.py
indico/types/submission.py
indico/types/submission_file.py
indico/types/user_metrics.py
indico/types/utils.py
indico/types/workflow.py
indico/types/workflow_metrics.py
indico_client.egg-info/PKG-INFO
indico_client.egg-info/SOURCES.txt
indico_client.egg-info/dependency_links.txt
indico_client.egg-info/requires.txt
indico_client.egg-info/top_level.txt
tests/integration/__init__.py
tests/integration/conftest.py
tests/integration/test_base_aioclient.py
tests/integration/test_base_client.py
tests/integration/data/__init__.py
tests/integration/data/async_datasets.py
tests/integration/data/datasets.py
tests/integration/queries/__init__.py
tests/integration/queries/test_custom_blueprint.py
