Metadata-Version: 2.1
Name: indico-client
Version: 6.14.1
Summary: A Python Wrapper for indico app API.
Home-page: https://github.com/IndicoDataSolutions/indico-client-python
Author: indico
Author-email: engineering@indico.io
License: MIT License (See LICENSE)
Platform: UNKNOWN
Provides-Extra: all
Provides-Extra: datasets
Provides-Extra: deserialization
Provides-Extra: exports
License-File: LICENSE
License-File: AUTHORS
